gender_detection_local/UpdateModel.py
gender_detection_local/__init__.py
gender_detection_local/extract_data.py
gender_detection_local/gender_detection.py
gender_detection_local/image_manipulation.py
gender_detection_local-0.2.19.dist-info/METADATA
gender_detection_local-0.2.19.dist-info/WHEEL
gender_detection_local-0.2.19.dist-info/top_level.txt
gender_detection_local-0.2.19.dist-info/RECORD
