Metadata-Version: 2.1
Name: gender-detection-local
Version: 0.2.19
Summary: PyPI Package for gender detection
Home-page: https://github.com/circles-zone/gender-detection-local-python-package
Author: Circles
Author-email: info@circles.zone
Classifier: Programming Language :: Python :: 3
Classifier: License :: Other/Proprietary License
Classifier: Operating System :: OS Independent
Requires-Dist: tensorflow >=2.13.0
Requires-Dist: logzio-python-handler >=4.1.0
Requires-Dist: opencv-python >=4.7.0.72
Requires-Dist: opencv-python-headless >=4.7.0.72
Requires-Dist: PyMySQL >=1.0.2
Requires-Dist: python-dotenv >=1.0.0
Requires-Dist: scikit-learn >=1.3.0
Requires-Dist: tqdm >=4.66.1
Requires-Dist: database-infrastructure-local >=0.0.11
Requires-Dist: gender-local >=0.0.3
Requires-Dist: logger-local >=0.0.51
Requires-Dist: boto3
